{
    "BaseSpDef": 73,
    "Gender": "♂♀両方",
    "Weight": 3.3,
    "AllAbilities": [
        "てつのトゲ",
        "ひらいしん",
        "がんじょう"
    ],
    "BaseSpeed": 96,
    "Types": [
        "でんき",
        "はがね"
    ],
    "BaseSpAtk": 40,
    "NormalAbilities": [
        "てつのトゲ",
        "ひらいしん"
    ],
    "Learnset": [
        "たいあたり",
        "ほっぺすりすり",
        "まるくなる",
        "じゅうでん",
        "でんきショック",
        "とどめばり",
        "スパーク",
        "ミサイルばり",
        "でんじふゆう",
        "びりびりちくちく",
        "ほうでん",
        "エレキフィールド",
        "ワイルドボルト",
        "ニードルガード",
        "はかいこうせん",
        "ギガインパクト",
        "でんじは",
        "リフレクター",
        "ねむる",
        "どろぼう",
        "いびき",
        "まもる",
        "メロメロ",
        "からげんき",
        "スピードスター",
        "てだすけ",
        "とびはねる",
        "とんぼがえり",
        "しっぺがえし",
        "ダメおし",
        "なげつける",
        "りんしょう",
        "ボルトチェンジ",
        "エレキネット",
        "かいでんぱ",
        "10まんボルト",
        "かみなり",
        "こうそくいどう",
        "みがわり",
        "きしかいせい",
        "こらえる",
        "ねごと",
        "アンコール",
        "アイアンテール",
        "ジャイロボール",
        "どくづき",
        "しねんのずつき",
        "アイアンヘッド",
        "くさむすび",
        "エレキボール",
        "ふるいたてる",
        "じたばた",
        "プレゼント",
        "ねこだまし",
        "ねがいごと",
        "くすぐる",
        "チャームボイス",
        "アイアンローラー",
        "ライジングボルト",
        "てっていこうせん"
    ],
    "HiddenAbility": "がんじょう",
    "Height": 0.3,
    "Category": "通常ポケモン",
    "BaseHP": 65,
    "EggGroups": [
        "陸上",
        "妖精"
    ],
    "BaseDef": 63,
    "BaseAtk": 98
}