{
    "BaseSpDef": 40,
    "Gender": "♂♀両方",
    "Weight": 4.8,
    "AllAbilities": [
        "ふしょく",
        "どんかん"
    ],
    "BaseSpeed": 77,
    "Types": [
        "どく",
        "ほのお"
    ],
    "BaseSpAtk": 71,
    "NormalAbilities": [
        "ふしょく"
    ],
    "Learnset": [
        "ひっかく",
        "どくガス",
        "スモッグ",
        "ひのこ",
        "どくどくのキバ",
        "あまいかおり",
        "わるだくみ",
        "やきつくす",
        "ベノムショック",
        "りゅうのはどう",
        "ベノムトラップ",
        "かえんほうしゃ",
        "どくどく",
        "がむしゃら",
        "でんじは",
        "ねむる",
        "どろぼう",
        "いびき",
        "まもる",
        "メロメロ",
        "ふくろだたき",
        "おにび",
        "からげんき",
        "スピードスター",
        "てだすけ",
        "しっぺがえし",
        "なげつける",
        "シャドークロー",
        "りんしょう",
        "だいもんじ",
        "きゅうけつ",
        "みがわり",
        "ヘドロばくだん",
        "こらえる",
        "ねごと",
        "アイアンテール",
        "ねっぷう",
        "ちょうはつ",
        "オーバーヒート",
        "ドラゴンクロー",
        "どくづき",
        "ダストシュート",
        "ヘドロウェーブ",
        "イカサマ",
        "すなかけ",
        "どろかけ",
        "ねこだまし",
        "ゲップ",
        "スケイルショット",
        "はいよるいちげき"
    ],
    "HiddenAbility": "どんかん",
    "Height": 0.6,
    "Category": "通常ポケモン",
    "BaseHP": 48,
    "EggGroups": [
        "怪獣",
        "ドラゴン"
    ],
    "BaseDef": 40,
    "BaseAtk": 44
}