{
    "BaseDef": 105,
    "BaseSpeed": 80,
    "NormalAbilities": [
        "ふゆう"
    ],
    "Height": 0.3,
    "HiddenAbility": "なし",
    "Learnset": [
        "ねむる",
        "ねんりき",
        "スピードスター",
        "まもる",
        "サイケこうせん",
        "ふういん",
        "じんつうりき",
        "あまえる",
        "サイコキネシス",
        "おだてる",
        "みらいよち",
        "まねっこ",
        "いやしのねがい",
        "ほのおのパンチ",
        "れいとうパンチ",
        "かみなりパンチ",
        "はかいこうせん",
        "ギガインパクト",
        "でんじは",
        "ひかりのかべ",
        "リフレクター",
        "しんぴのまもり",
        "いびき",
        "すなあらし",
        "あまごい",
        "にほんばれ",
        "からげんき",
        "てだすけ",
        "とんぼがえり",
        "なげつける",
        "ドレインパンチ",
        "サイコカッター",
        "トリックルーム",
        "ワンダールーム",
        "マジックルーム",
        "りんしょう",
        "アクロバット",
        "ドレインキッス",
        "れいとうビーム",
        "ふぶき",
        "10まんボルト",
        "かみなり",
        "ゆびをふる",
        "トライアタック",
        "みがわり",
        "サイコショック",
        "こらえる",
        "ねごと",
        "バトンタッチ",
        "アンコール",
        "アイアンテール",
        "シャドーボール",
        "トリック",
        "スキルスワップ",
        "めいそう",
        "エナジーボール",
        "わるだくみ",
        "しねんのずつき",
        "ステルスロック",
        "くさむすび",
        "アシストパワー",
        "サイドチェンジ",
        "じゃれつく",
        "マジカルシャイン",
        "ワイドフォース"
    ],
    "BaseAtk": 105,
    "BaseSpDef": 105,
    "BaseHP": 80,
    "EggGroups": [
        "タマゴ未発見"
    ],
    "Gender": "不明",
    "AllAbilities": [
        "ふゆう"
    ],
    "Weight": 0.3,
    "Category": "準伝説ポケモン",
    "BaseSpAtk": 105,
    "Types": [
        "エスパー"
    ]
}