{
    "BaseDef": 115,
    "BaseSpeed": 75,
    "NormalAbilities": [
        "グラスメイカー"
    ],
    "Height": 1.9,
    "HiddenAbility": "テレパシー",
    "Learnset": [
        "このは",
        "いわくだき",
        "からにこもる",
        "かなしばり",
        "やどりぎのタネ",
        "メガドレイン",
        "ふきとばし",
        "つのでつく",
        "こわいかお",
        "ウッドホーン",
        "しねんのずつき",
        "くろいまなざし",
        "しぜんのいかり",
        "ウッドハンマー",
        "メガホーン",
        "ロケットずつき",
        "グラスフィールド",
        "メガトンパンチ",
        "はかいこうせん",
        "ギガインパクト",
        "ソーラービーム",
        "ひかりのかべ",
        "リフレクター",
        "しんぴのまもり",
        "ねむる",
        "いわなだれ",
        "いびき",
        "まもる",
        "ギガドレイン",
        "にほんばれ",
        "からげんき",
        "リベンジ",
        "かわらわり",
        "がんせきふうじ",
        "タネマシンガン",
        "しっぺがえし",
        "なげつける",
        "パワースワップ",
        "ガードスワップ",
        "りんしょう",
        "バークアウト",
        "みねうち",
        "スマートホーン",
        "ぶんまわす",
        "つるぎのまい",
        "みがわり",
        "こらえる",
        "ねごと",
        "ちょうはつ",
        "ばかぢから",
        "てっぺき",
        "ビルドアップ",
        "めいそう",
        "インファイト",
        "タネばくだん",
        "きあいだま",
        "エナジーボール",
        "ストーンエッジ",
        "くさむすび",
        "アシストパワー",
        "ふるいたてる",
        "マジカルシャイン",
        "DDラリアット",
        "10まんばりき"
    ],
    "BaseAtk": 130,
    "BaseSpDef": 95,
    "BaseHP": 70,
    "EggGroups": [
        "タマゴ未発見"
    ],
    "Gender": "不明",
    "AllAbilities": [
        "グラスメイカー",
        "テレパシー"
    ],
    "Weight": 45.5,
    "Category": "準伝説ポケモン",
    "BaseSpAtk": 85,
    "Types": [
        "くさ",
        "フェアリー"
    ]
}