{
    "BaseDef": 80,
    "BaseSpeed": 90,
    "NormalAbilities": [
        "はやおき",
        "きもったま"
    ],
    "Height": 2.2,
    "HiddenAbility": "せいしんりょく",
    "Learnset": [
        "はたく",
        "しっぽをふる",
        "なきごえ",
        "ねこだまし",
        "かみつく",
        "ふみつけ",
        "きあいだめ",
        "ずつき",
        "ふいうち",
        "ダブルアタック",
        "かみくだく",
        "こらえる",
        "きしかいせい",
        "げきりん",
        "とっておき",
        "メガトンパンチ",
        "メガトンキック",
        "ほのおのパンチ",
        "れいとうパンチ",
        "かみなりパンチ",
        "はかいこうせん",
        "ギガインパクト",
        "ソーラービーム",
        "あなをほる",
        "しんぴのまもり",
        "ねむる",
        "いわなだれ",
        "どろぼう",
        "いびき",
        "まもる",
        "こごえるかぜ",
        "メロメロ",
        "すなあらし",
        "あまごい",
        "にほんばれ",
        "あられ",
        "うずしお",
        "ふくろだたき",
        "からげんき",
        "てだすけ",
        "かわらわり",
        "がんせきふうじ",
        "ダメおし",
        "なげつける",
        "ドレインパンチ",
        "ゆきなだれ",
        "シャドークロー",
        "りんしょう",
        "かたきうち",
        "じならし",
        "のしかかり",
        "かえんほうしゃ",
        "ハイドロポンプ",
        "なみのり",
        "れいとうビーム",
        "ふぶき",
        "けたぐり",
        "10まんボルト",
        "かみなり",
        "じしん",
        "だいもんじ",
        "みがわり",
        "ねごと",
        "アイアンテール",
        "シャドーボール",
        "さわぐ",
        "きあいだま",
        "ふるいたてる",
        "すてみタックル",
        "かなしばり",
        "カウンター",
        "がむしゃら",
        "アームハンマー",
        "ともえなげ",
        "だいちのはどう"
    ],
    "BaseAtk": 95,
    "BaseSpDef": 80,
    "BaseHP": 105,
    "EggGroups": [
        "怪獣"
    ],
    "Gender": "♀のみ",
    "AllAbilities": [
        "はやおき",
        "きもったま",
        "せいしんりょく"
    ],
    "Weight": 80.0,
    "Category": "通常ポケモン",
    "BaseSpAtk": 40,
    "Types": [
        "ノーマル"
    ]
}