{
    "BaseDef": 95,
    "BaseSpeed": 85,
    "NormalAbilities": [
        "すいすい",
        "スナイパー"
    ],
    "Height": 1.8,
    "HiddenAbility": "しめりけ",
    "Learnset": [
        "あくび",
        "みずでっぽう",
        "えんまく",
        "にらみつける",
        "うずしお",
        "たつまき",
        "きあいだめ",
        "りゅうのいぶき",
        "バブルこうせん",
        "こうそくいどう",
        "とぎすます",
        "りゅうのはどう",
        "ハイドロポンプ",
        "りゅうのまい",
        "あまごい",
        "はかいこうせん",
        "ギガインパクト",
        "ねむる",
        "いびき",
        "まもる",
        "こごえるかぜ",
        "メロメロ",
        "あられ",
        "からげんき",
        "スピードスター",
        "ダイビング",
        "とびはねる",
        "しおみず",
        "りんしょう",
        "ワイドブレイカー",
        "のしかかり",
        "なみのり",
        "れいとうビーム",
        "ふぶき",
        "たきのぼり",
        "みがわり",
        "げきりん",
        "こらえる",
        "ねごと",
        "だくりゅう",
        "ラスターカノン",
        "アイアンヘッド",
        "ねっとう",
        "ぼうふう",
        "アクアブレイク",
        "かなしばり",
        "オーロラビーム",
        "はねる",
        "じたばた",
        "オクタンほう",
        "みずのはどう",
        "クリアスモッグ",
        "スケイルショット",
        "クイックターン",
        "りゅうせいぐん"
    ],
    "BaseAtk": 95,
    "BaseSpDef": 95,
    "BaseHP": 75,
    "EggGroups": [
        "水中1",
        "ドラゴン"
    ],
    "Gender": "♂♀両方",
    "AllAbilities": [
        "すいすい",
        "スナイパー",
        "しめりけ"
    ],
    "Weight": 152.0,
    "Category": "通常ポケモン",
    "BaseSpAtk": 95,
    "Types": [
        "みず",
        "ドラゴン"
    ]
}