{
    "BaseSpDef": 65,
    "Gender": "♂♀両方",
    "Weight": 0.5,
    "AllAbilities": [
        "いやしのこころ",
        "アロマベール"
    ],
    "BaseSpeed": 23,
    "Types": [
        "フェアリー"
    ],
    "BaseSpAtk": 63,
    "NormalAbilities": [
        "いやしのこころ"
    ],
    "Learnset": [
        "あまいかおり",
        "ようせいのかぜ",
        "てんしのキッス",
        "エコーボイス",
        "ドレインキッス",
        "アロマセラピー",
        "メロメロ",
        "じたばた",
        "ミストフィールド",
        "サイコキネシス",
        "あまえる",
        "めいそう",
        "ムーンフォース",
        "スキルスワップ",
        "ひかりのかべ",
        "リフレクター",
        "ねむる",
        "いびき",
        "まもる",
        "あまごい",
        "にほんばれ",
        "からげんき",
        "てだすけ",
        "うそなき",
        "トリックルーム",
        "りんしょう",
        "10まんボルト",
        "みがわり",
        "こらえる",
        "ねごと",
        "アンコール",
        "ジャイロボール",
        "エナジーボール",
        "わるだくみ",
        "ラスターカノン",
        "サイドチェンジ",
        "マジカルシャイン",
        "かなしばり",
        "ねがいごと",
        "おさきにどうぞ",
        "ミストバースト"
    ],
    "HiddenAbility": "アロマベール",
    "Height": 0.2,
    "Category": "通常ポケモン",
    "BaseHP": 78,
    "EggGroups": [
        "妖精"
    ],
    "BaseDef": 60,
    "BaseAtk": 52
}