{
    "BaseDef": 85,
    "BaseSpeed": 40,
    "NormalAbilities": [
        "はりきり",
        "てんのめぐみ"
    ],
    "Height": 0.6,
    "HiddenAbility": "きょううん",
    "Learnset": [
        "ようせいのかぜ",
        "なきごえ",
        "てんしのキッス",
        "はたく",
        "いのちのしずく",
        "あまえる",
        "げんしのちから",
        "あくび",
        "ゆびをふる",
        "おさきにどうぞ",
        "すてみタックル",
        "しんぴのまもり",
        "このゆびとまれ",
        "バトンタッチ",
        "とっておき",
        "ねがいごと",
        "メガトンパンチ",
        "メガトンキック",
        "そらをとぶ",
        "はかいこうせん",
        "ギガインパクト",
        "マジカルリーフ",
        "ソーラービーム",
        "でんじは",
        "ひかりのかべ",
        "リフレクター",
        "ねむる",
        "いびき",
        "まもる",
        "はがねのつばさ",
        "メロメロ",
        "あまごい",
        "にほんばれ",
        "からげんき",
        "スピードスター",
        "てだすけ",
        "かわらわり",
        "ふういん",
        "なげつける",
        "ドレインパンチ",
        "りんしょう",
        "かたきうち",
        "ドレインキッス",
        "マジカルフレイム",
        "スマートホーン",
        "のしかかり",
        "かえんほうしゃ",
        "サイコキネシス",
        "だいもんじ",
        "トライアタック",
        "みがわり",
        "サイコショック",
        "こらえる",
        "ねごと",
        "アンコール",
        "シャドーボール",
        "みらいよち",
        "さわぐ",
        "ねっぷう",
        "トリック",
        "ハイパーボイス",
        "わるだくみ",
        "しねんのずつき",
        "くさむすび",
        "アシストパワー",
        "ふるいたてる",
        "じゃれつく",
        "マジカルシャイン",
        "つつく",
        "プレゼント",
        "あさのひざし",
        "じんつうりき",
        "つばめがえし",
        "サイコシフト",
        "ダブルウイング"
    ],
    "BaseAtk": 40,
    "BaseSpDef": 105,
    "BaseHP": 55,
    "EggGroups": [
        "飛行",
        "妖精"
    ],
    "Gender": "♂♀両方",
    "AllAbilities": [
        "はりきり",
        "てんのめぐみ",
        "きょううん"
    ],
    "Weight": 3.2,
    "Category": "通常ポケモン",
    "BaseSpAtk": 80,
    "Types": [
        "フェアリー",
        "ひこう"
    ]
}