{
    "BaseDef": 80,
    "BaseSpeed": 121,
    "NormalAbilities": [
        "さいせいりょく"
    ],
    "Height": 1.4,
    "HiddenAbility": "なし",
    "Learnset": [
        "おどろかす",
        "かぜおこし",
        "にらみつける",
        "いばる",
        "かみつく",
        "エアカッター",
        "こうそくいどう",
        "おいかぜ",
        "エアスラッシュ",
        "かみくだく",
        "じんつうりき",
        "さわぐ",
        "アームハンマー",
        "あまごい",
        "ぼうふう",
        "あばれる",
        "そらをとぶ",
        "はかいこうせん",
        "ギガインパクト",
        "ねむる",
        "どろぼう",
        "いびき",
        "まもる",
        "こわいかお",
        "こごえるかぜ",
        "メロメロ",
        "からげんき",
        "リベンジ",
        "かわらわり",
        "ウェザーボール",
        "とんぼがえり",
        "しっぺがえし",
        "ダメおし",
        "なげつける",
        "りんしょう",
        "アクロバット",
        "ぶんまわす",
        "のしかかり",
        "サイコキネシス",
        "みがわり",
        "ヘドロばくだん",
        "こらえる",
        "ねごと",
        "アイアンテール",
        "ねっぷう",
        "ちょうはつ",
        "ばかぢから",
        "ビルドアップ",
        "あくのはどう",
        "きあいだま",
        "わるだくみ",
        "くさむすび",
        "ヘドロウェーブ",
        "イカサマ",
        "うっぷんばらし"
    ],
    "BaseAtk": 100,
    "BaseSpDef": 90,
    "BaseHP": 79,
    "EggGroups": [
        "タマゴ未発見"
    ],
    "Gender": "♂のみ",
    "AllAbilities": [
        "さいせいりょく"
    ],
    "Weight": 63.0,
    "Category": "準伝説ポケモン",
    "BaseSpAtk": 110,
    "Types": [
        "ひこう"
    ]
}