{
    "BaseDef": 90,
    "BaseSpeed": 65,
    "NormalAbilities": [
        "あついしぼう",
        "アイスボディ"
    ],
    "Height": 1.4,
    "HiddenAbility": "どんかん",
    "Learnset": [
        "かみくだく",
        "なきごえ",
        "みずでっぽう",
        "まるくなる",
        "こおりのキバ",
        "いばる",
        "ころがる",
        "こなゆき",
        "ねむる",
        "いびき",
        "しおみず",
        "オーロラビーム",
        "アンコール",
        "のしかかり",
        "なみのり",
        "ふぶき",
        "あられ",
        "ぜったいれいど",
        "はかいこうせん",
        "ギガインパクト",
        "いわなだれ",
        "まもる",
        "こごえるかぜ",
        "メロメロ",
        "あまごい",
        "うずしお",
        "からげんき",
        "ダイビング",
        "がんせきふうじ",
        "つららばり",
        "ゆきなだれ",
        "りんしょう",
        "じならし",
        "じだんだ",
        "つるぎのまい",
        "ハイドロポンプ",
        "れいとうビーム",
        "じしん",
        "たきのぼり",
        "みがわり",
        "こらえる",
        "ねごと",
        "アイアンテール",
        "アイアンヘッド",
        "ヘビーボンバー",
        "アクアブレイク",
        "ボディプレス",
        "じわれ",
        "のろい",
        "はらだいこ",
        "たくわえる",
        "はきだす",
        "のみこむ",
        "あくび",
        "みずのはどう",
        "アクアリング",
        "アイアンローラー"
    ],
    "BaseAtk": 80,
    "BaseSpDef": 90,
    "BaseHP": 110,
    "EggGroups": [
        "水中1",
        "陸上"
    ],
    "Gender": "♂♀両方",
    "AllAbilities": [
        "あついしぼう",
        "アイスボディ",
        "どんかん"
    ],
    "Weight": 150.6,
    "Category": "通常ポケモン",
    "BaseSpAtk": 95,
    "Types": [
        "こおり",
        "みず"
    ]
}