{
    "BaseSpDef": 123,
    "Gender": "♂♀両方",
    "Weight": 81.5,
    "AllAbilities": [
        "どくのトゲ",
        "どくしゅ",
        "てきおうりょく"
    ],
    "BaseSpeed": 44,
    "Types": [
        "どく",
        "ドラゴン"
    ],
    "BaseSpAtk": 97,
    "NormalAbilities": [
        "どくのトゲ",
        "どくしゅ"
    ],
    "Learnset": [
        "たいあたり",
        "えんまく",
        "みずでっぽう",
        "ようかいえき",
        "しっぽをふる",
        "かげぶんしん",
        "ポイズンテール",
        "みずのはどう",
        "どくどく",
        "りゅうのはどう",
        "アクアテール",
        "ヘドロばくだん",
        "ハイドロポンプ",
        "げきりん",
        "はかいこうせん",
        "ギガインパクト",
        "ねむる",
        "いびき",
        "まもる",
        "こごえるかぜ",
        "メロメロ",
        "あまごい",
        "あられ",
        "からげんき",
        "ダイビング",
        "とびはねる",
        "ベノムショック",
        "りんしょう",
        "なみのり",
        "10まんボルト",
        "かみなり",
        "たきのぼり",
        "みがわり",
        "こらえる",
        "ねごと",
        "アイアンテール",
        "シャドーボール",
        "どくびし",
        "きあいだま",
        "ダストシュート",
        "ヘドロウェーブ",
        "ねっとう",
        "じゃれつく",
        "ベノムトラップ",
        "くろいきり",
        "とける",
        "たつまき",
        "ドラゴンテール",
        "スケイルショット",
        "クイックターン",
        "りゅうせいぐん"
    ],
    "HiddenAbility": "てきおうりょく",
    "Height": 1.8,
    "Category": "通常ポケモン",
    "BaseHP": 65,
    "EggGroups": [
        "水中1",
        "ドラゴン"
    ],
    "BaseDef": 90,
    "BaseAtk": 75
}