{
    "BaseDef": 43,
    "BaseSpeed": 48,
    "NormalAbilities": [
        "ぼうおん"
    ],
    "Height": 1.0,
    "HiddenAbility": "きもったま",
    "Learnset": [
        "かみつく",
        "はたく",
        "おどろかす",
        "とおぼえ",
        "エコーボイス",
        "ねむる",
        "ねごと",
        "ふみつけ",
        "ほえる",
        "ちょうおんぱ",
        "さわぐ",
        "いやなおと",
        "ハイパーボイス",
        "メガトンパンチ",
        "メガトンキック",
        "ほのおのパンチ",
        "れいとうパンチ",
        "かみなりパンチ",
        "ソーラービーム",
        "いわなだれ",
        "いびき",
        "まもる",
        "こごえるかぜ",
        "メロメロ",
        "あまごい",
        "にほんばれ",
        "からげんき",
        "かわらわり",
        "うそなき",
        "がんせきふうじ",
        "なげつける",
        "りんしょう",
        "かたきうち",
        "じならし",
        "じだんだ",
        "のしかかり",
        "かえんほうしゃ",
        "れいとうビーム",
        "ふぶき",
        "けたぐり",
        "じしん",
        "だいもんじ",
        "みがわり",
        "こらえる",
        "シャドーボール",
        "ちょうはつ",
        "オーバーヒート",
        "しねんのずつき",
        "ふるいたてる",
        "ふきとばし",
        "とっしん",
        "えんまく",
        "がむしゃら",
        "じんつうりき",
        "アームハンマー",
        "ともえなげ",
        "チャームボイス"
    ],
    "BaseAtk": 71,
    "BaseSpDef": 43,
    "BaseHP": 84,
    "EggGroups": [
        "怪獣",
        "陸上"
    ],
    "Gender": "♂♀両方",
    "AllAbilities": [
        "ぼうおん",
        "きもったま"
    ],
    "Weight": 40.5,
    "Category": "通常ポケモン",
    "BaseSpAtk": 71,
    "Types": [
        "ノーマル"
    ]
}