{
    "BaseDef": 50,
    "BaseSpeed": 44,
    "NormalAbilities": [
        "アイスボディ",
        "ゆきがくれ"
    ],
    "Height": 0.4,
    "HiddenAbility": "くだけるよろい",
    "Learnset": [
        "おどろかす",
        "かたくなる",
        "ちょうはつ",
        "しろいきり",
        "こごえるかぜ",
        "ゆきなだれ",
        "あられ",
        "つららばり",
        "さわぐ",
        "とける",
        "ミラーコート",
        "れいとうビーム",
        "ふぶき",
        "ぜったいれいど",
        "ひかりのかべ",
        "じばく",
        "ねむる",
        "いびき",
        "まもる",
        "メロメロ",
        "あまごい",
        "からげんき",
        "ふういん",
        "りんしょう",
        "みがわり",
        "こらえる",
        "ねごと",
        "ハイパーボイス",
        "てっぺき",
        "ラスターカノン",
        "サイドチェンジ",
        "だいばくはつ",
        "でんじふゆう",
        "こおりのつぶて",
        "ボディパージ",
        "つららおとし",
        "オーロラベール"
    ],
    "BaseAtk": 50,
    "BaseSpDef": 60,
    "BaseHP": 36,
    "EggGroups": [
        "鉱物"
    ],
    "Gender": "♂♀両方",
    "AllAbilities": [
        "アイスボディ",
        "ゆきがくれ",
        "くだけるよろい"
    ],
    "Weight": 5.7,
    "Category": "通常ポケモン",
    "BaseSpAtk": 65,
    "Types": [
        "こおり"
    ]
}