{
    "BaseSpDef": 35,
    "Gender": "♂のみ",
    "Weight": 21.0,
    "AllAbilities": [
        "こんじょう",
        "ふくつのこころ",
        "やるき"
    ],
    "BaseSpeed": 35,
    "Types": [
        "かくとう"
    ],
    "BaseSpAtk": 35,
    "NormalAbilities": [
        "こんじょう",
        "ふくつのこころ"
    ],
    "Learnset": [
        "たいあたり",
        "てだすけ",
        "ねこだまし",
        "きあいだめ",
        "メガトンパンチ",
        "メガトンキック",
        "ねむる",
        "いわなだれ",
        "どろぼう",
        "いびき",
        "まもる",
        "メロメロ",
        "あまごい",
        "にほんばれ",
        "からげんき",
        "スピードスター",
        "かわらわり",
        "ローキック",
        "りんしょう",
        "かたきうち",
        "じならし",
        "のしかかり",
        "けたぐり",
        "じしん",
        "みがわり",
        "こらえる",
        "ねごと",
        "さわぐ",
        "ビルドアップ",
        "ふるいたてる",
        "カウンター",
        "とびひざげり",
        "こころのめ",
        "マッハパンチ",
        "こうそくスピン",
        "フェイント",
        "しんくうは",
        "バレットパンチ"
    ],
    "HiddenAbility": "やるき",
    "Height": 0.7,
    "Category": "通常ポケモン",
    "BaseHP": 35,
    "EggGroups": [
        "タマゴ未発見"
    ],
    "BaseDef": 35,
    "BaseAtk": 35
}