{
    "BaseDef": 180,
    "BaseSpeed": 70,
    "NormalAbilities": [
        "シェルアーマー",
        "スキルリンク"
    ],
    "Height": 1.5,
    "HiddenAbility": "ぼうじん",
    "Learnset": [
        "つららばり",
        "ハイドロポンプ",
        "からをやぶる",
        "どくびし",
        "からにこもる",
        "ちょうおんぱ",
        "オーロラビーム",
        "まもる",
        "たいあたり",
        "みずでっぽう",
        "にらみつける",
        "つららおとし",
        "まきびし",
        "うずしお",
        "シェルブレード",
        "てっぺき",
        "れいとうビーム",
        "こおりのつぶて",
        "ミサイルばり",
        "はかいこうせん",
        "ギガインパクト",
        "いやなおと",
        "ひかりのかべ",
        "じばく",
        "ねむる",
        "いびき",
        "こごえるかぜ",
        "メロメロ",
        "あまごい",
        "あられ",
        "からげんき",
        "スピードスター",
        "ダイビング",
        "ウェザーボール",
        "マッドショット",
        "ロックブラスト",
        "しおみず",
        "しっぺがえし",
        "ゆきなだれ",
        "りんしょう",
        "スマートホーン",
        "なみのり",
        "ふぶき",
        "トライアタック",
        "みがわり",
        "こらえる",
        "ねごと",
        "どくづき",
        "アクアブレイク",
        "バブルこうせん",
        "みずのはどう",
        "アクアリング",
        "いのちのしずく",
        "アイアンローラー"
    ],
    "BaseAtk": 95,
    "BaseSpDef": 45,
    "BaseHP": 50,
    "EggGroups": [
        "水中3"
    ],
    "Gender": "♂♀両方",
    "AllAbilities": [
        "シェルアーマー",
        "スキルリンク",
        "ぼうじん"
    ],
    "Weight": 132.5,
    "Category": "通常ポケモン",
    "BaseSpAtk": 85,
    "Types": [
        "みず",
        "こおり"
    ]
}