{
    "BaseDef": 60,
    "BaseSpeed": 10,
    "NormalAbilities": [
        "わたげ",
        "さいせいりょく"
    ],
    "Height": 0.4,
    "HiddenAbility": "ほうし",
    "Learnset": [
        "このは",
        "うたう",
        "こうそくスピン",
        "あまいかおり",
        "はっぱカッター",
        "りんしょう",
        "グラスミキサー",
        "こうごうせい",
        "ハイパーボイス",
        "アロマセラピー",
        "リーフストーム",
        "マジカルリーフ",
        "ソーラービーム",
        "ひかりのかべ",
        "ねむる",
        "いびき",
        "まもる",
        "ギガドレイン",
        "あまえる",
        "メロメロ",
        "にほんばれ",
        "からげんき",
        "てだすけ",
        "タネマシンガン",
        "グラスフィールド",
        "みがわり",
        "こらえる",
        "ねごと",
        "エナジーボール",
        "くさむすび",
        "かふんだんご",
        "やどりぎのタネ",
        "せいちょう",
        "どくのこな",
        "しびれごな",
        "ねむりごな",
        "なやみのタネ",
        "グラススライダー"
    ],
    "BaseAtk": 40,
    "BaseSpDef": 60,
    "BaseHP": 40,
    "EggGroups": [
        "植物"
    ],
    "Gender": "♂♀両方",
    "AllAbilities": [
        "わたげ",
        "さいせいりょく",
        "ほうし"
    ],
    "Weight": 2.2,
    "Category": "通常ポケモン",
    "BaseSpAtk": 40,
    "Types": [
        "くさ"
    ]
}