{
    "BaseSpDef": 103,
    "Gender": "♀のみ",
    "Weight": 5.1,
    "AllAbilities": [
        "いやしのこころ",
        "きけんよち",
        "マジックミラー"
    ],
    "BaseSpeed": 29,
    "Types": [
        "エスパー",
        "フェアリー"
    ],
    "BaseSpAtk": 136,
    "NormalAbilities": [
        "いやしのこころ",
        "きけんよち"
    ],
    "Learnset": [
        "サイコカッター",
        "ぶんまわす",
        "ねんりき",
        "なかよくする",
        "いのちのしずく",
        "チャームボイス",
        "アロマセラピー",
        "サイケこうせん",
        "いやしのはどう",
        "マジカルシャイン",
        "めいそう",
        "サイコキネシス",
        "いやしのねがい",
        "まほうのこな",
        "はかいこうせん",
        "ギガインパクト",
        "マジカルリーフ",
        "でんじは",
        "ひかりのかべ",
        "しんぴのまもり",
        "ねむる",
        "いびき",
        "まもる",
        "ギガドレイン",
        "あまえる",
        "メロメロ",
        "からげんき",
        "てだすけ",
        "ふういん",
        "パワースワップ",
        "ガードスワップ",
        "シャドークロー",
        "トリックルーム",
        "ワンダールーム",
        "マジックルーム",
        "りんしょう",
        "ドレインキッス",
        "マジカルフレイム",
        "つるぎのまい",
        "みがわり",
        "サイコショック",
        "こらえる",
        "ねごと",
        "バトンタッチ",
        "シャドーボール",
        "みらいよち",
        "スキルスワップ",
        "あくのはどう",
        "パワーウィップ",
        "アシストパワー",
        "じゃれつく",
        "おさきにどうぞ",
        "さきおくり",
        "ほっぺすりすり",
        "アロマミスト",
        "ワイドフォース",
        "ミストバースト"
    ],
    "HiddenAbility": "マジックミラー",
    "Height": 2.1,
    "Category": "通常ポケモン",
    "BaseHP": 57,
    "EggGroups": [
        "妖精"
    ],
    "BaseDef": 95,
    "BaseAtk": 90
}