{
    "BaseDef": 55,
    "BaseSpeed": 25,
    "NormalAbilities": [
        "ほおぶくろ"
    ],
    "Height": 0.3,
    "HiddenAbility": "くいしんぼう",
    "Learnset": [
        "たいあたり",
        "しっぽをふる",
        "かみつく",
        "ほおばる",
        "たくわえる",
        "のみこむ",
        "はきだす",
        "のしかかり",
        "ねむる",
        "カウンター",
        "タネマシンガン",
        "いかりのまえば",
        "ゲップ",
        "あなをほる",
        "どろぼう",
        "いびき",
        "まもる",
        "メロメロ",
        "からげんき",
        "マッドショット",
        "しっぺがえし",
        "ダメおし",
        "なげつける",
        "りんしょう",
        "スイープビンタ",
        "ぶんまわす",
        "ドわすれ",
        "みがわり",
        "こらえる",
        "ねごと",
        "アイアンテール",
        "かみくだく",
        "さわぐ",
        "ハイパーボイス",
        "ジャイロボール",
        "タネばくだん",
        "まるくなる",
        "はらだいこ",
        "ころがる",
        "とっておき"
    ],
    "BaseAtk": 55,
    "BaseSpDef": 35,
    "BaseHP": 70,
    "EggGroups": [
        "陸上"
    ],
    "Gender": "♂♀両方",
    "AllAbilities": [
        "ほおぶくろ",
        "くいしんぼう"
    ],
    "Weight": 2.5,
    "Category": "通常ポケモン",
    "BaseSpAtk": 35,
    "Types": [
        "ノーマル"
    ]
}