{
    "BaseDef": 44,
    "BaseSpeed": 85,
    "NormalAbilities": [
        "にげあし",
        "ぶきよう"
    ],
    "Height": 0.4,
    "HiddenAbility": "じゅうなん",
    "Learnset": [
        "はねる",
        "はたく",
        "まるくなる",
        "つぶらなひとみ",
        "おさきにどうぞ",
        "でんこうせっか",
        "にどげり",
        "あまえる",
        "バトンタッチ",
        "ずつき",
        "こうそくいどう",
        "なかまづくり",
        "おだてる",
        "とびはねる",
        "いやしのねがい",
        "メガトンパンチ",
        "メガトンキック",
        "ほのおのパンチ",
        "れいとうパンチ",
        "かみなりパンチ",
        "ソーラービーム",
        "でんじは",
        "あなをほる",
        "ねむる",
        "いびき",
        "まもる",
        "メロメロ",
        "あまごい",
        "にほんばれ",
        "からげんき",
        "スピードスター",
        "てだすけ",
        "うそなき",
        "しっぺがえし",
        "ダメおし",
        "なげつける",
        "ドレインパンチ",
        "ローキック",
        "りんしょう",
        "かたきうち",
        "れいとうビーム",
        "けたぐり",
        "10まんボルト",
        "みがわり",
        "こらえる",
        "ねごと",
        "アンコール",
        "アイアンテール",
        "シャドーボール",
        "さわぐ",
        "ハイパーボイス",
        "コスモパワー",
        "くさむすび",
        "ふるいたてる",
        "じゃれつく",
        "じたばた",
        "てんしのキッス",
        "ねこだまし",
        "きあいパンチ",
        "フラフラダンス",
        "まねっこ",
        "すりかえ",
        "ダブルアタック",
        "ともえなげ",
        "トリプルアクセル"
    ],
    "BaseAtk": 66,
    "BaseSpDef": 56,
    "BaseHP": 55,
    "EggGroups": [
        "陸上",
        "人型"
    ],
    "Gender": "♂♀両方",
    "AllAbilities": [
        "にげあし",
        "ぶきよう",
        "じゅうなん"
    ],
    "Weight": 5.5,
    "Category": "通常ポケモン",
    "BaseSpAtk": 44,
    "Types": [
        "ノーマル"
    ]
}