{
    "BaseSpDef": 35,
    "Gender": "♂♀両方",
    "Weight": 19.5,
    "AllAbilities": [
        "こんじょう",
        "ノーガード",
        "ふくつのこころ"
    ],
    "BaseSpeed": 35,
    "Types": [
        "かくとう"
    ],
    "BaseSpAtk": 35,
    "NormalAbilities": [
        "こんじょう",
        "ノーガード"
    ],
    "Learnset": [
        "けたぐり",
        "にらみつける",
        "きあいだめ",
        "リベンジ",
        "ローキック",
        "はたきおとす",
        "こわいかお",
        "あてみなげ",
        "かいりき",
        "ダブルチョップ",
        "ビルドアップ",
        "ちきゅうなげ",
        "ばくれつパンチ",
        "クロスチョップ",
        "すてみタックル",
        "メガトンパンチ",
        "メガトンキック",
        "ほのおのパンチ",
        "れいとうパンチ",
        "かみなりパンチ",
        "あなをほる",
        "ひかりのかべ",
        "ねむる",
        "いわなだれ",
        "どろぼう",
        "いびき",
        "まもる",
        "メロメロ",
        "あまごい",
        "にほんばれ",
        "からげんき",
        "てだすけ",
        "かわらわり",
        "がんせきふうじ",
        "しっぺがえし",
        "なげつける",
        "りんしょう",
        "かたきうち",
        "じならし",
        "のしかかり",
        "かえんほうしゃ",
        "じしん",
        "ゆびをふる",
        "だいもんじ",
        "みがわり",
        "きしかいせい",
        "こらえる",
        "ねごと",
        "アンコール",
        "ばかぢから",
        "インファイト",
        "どくづき",
        "きあいだま",
        "ヘビーボンバー",
        "ふるいたてる",
        "じごくぐるま",
        "カウンター",
        "くすぐる",
        "バレットパンチ",
        "ファストガード",
        "コーチング"
    ],
    "HiddenAbility": "ふくつのこころ",
    "Height": 0.8,
    "Category": "通常ポケモン",
    "BaseHP": 70,
    "EggGroups": [
        "人型"
    ],
    "BaseDef": 50,
    "BaseAtk": 80
}